ftsim/__init__.py
ftsim/ft.db
ftsim/ftdb2.py
ftsim/ftlib4.py
ftsim/ftmain9.py
ftsim/ftmain9.save.py
ftsim/ftsim105.sql
ftsim/ftsim106.sql
ftsim-0.9.3.dist-info/LICENSE
ftsim-0.9.3.dist-info/METADATA
ftsim-0.9.3.dist-info/WHEEL
ftsim-0.9.3.dist-info/entry_points.txt
ftsim-0.9.3.dist-info/top_level.txt
ftsim-0.9.3.dist-info/RECORD
