Metadata-Version: 2.1
Name: ftsim
Version: 0.9.3
Summary: Simulates and visualises transport of loadunits in a warehouse environment.
Home-page: https://github.com/gerpark/ftsim
Author: Gerhard Sachs
Author-email: <g.w.sachs@gmx.de>
License: MIT
Keywords: tkinter,sqlite,threading,game
Platform: UNKNOWN
Classifier: Operating System :: OS Independent
Classifier: Intended Audience :: Developers
Classifier: Intended Audience :: End Users/Desktop
Classifier: Intended Audience :: Education
Classifier: License :: OSI Approved :: MIT License
Classifier: Programming Language :: Python :: 3
Classifier: Programming Language :: Python :: 3.6
License-File: LICENSE
